cad/CDS.py
cad/__init__.py
cad/main.py
cad/pyhik_mod.py
cad/tests/__init__.py
cad/tests/test_main.py
qcad-0.7.31.dist-info/LICENSE
qcad-0.7.31.dist-info/METADATA
qcad-0.7.31.dist-info/WHEEL
qcad-0.7.31.dist-info/top_level.txt
qcad-0.7.31.dist-info/RECORD
