Metadata-Version: 2.1
Name: qcad
Version: 0.7.31
Author: PunchyArchy
Author-email: ksmdrmvscthny@gmail.com
License-File: LICENSE
Requires-Dist: hikvisionapi
